py_compile_win_helpers.py
setup.py
py_compile_win_helpers.egg-info/PKG-INFO
py_compile_win_helpers.egg-info/SOURCES.txt
py_compile_win_helpers.egg-info/dependency_links.txt
py_compile_win_helpers.egg-info/top_level.txt