Metadata-Version: 1.0
Name: py-compile-win-helpers
Version: 1.0.2
Summary: Helpers to setup the environment to compile extensions for Python
Home-page: https://github.com/fabioz/py_compile_win_helpers
Author: Fabio Zadrozny
Author-email: UNKNOWN
License: UNKNOWN
Platform: UNKNOWN
